ama/__init__.py
ama/terminal.py
ama/tk.py
ama/validator.py
ama-0.2.dist-info/DESCRIPTION.rst
ama-0.2.dist-info/METADATA
ama-0.2.dist-info/RECORD
ama-0.2.dist-info/WHEEL
ama-0.2.dist-info/metadata.json
ama-0.2.dist-info/top_level.txt
